nbainjuries/__init__.py
nbainjuries/_constants.py
nbainjuries/_exceptions.py
nbainjuries/_parser.py
nbainjuries/_parser_asy.py
nbainjuries/_util.py
nbainjuries/injury.py
nbainjuries/injury_asy.py
nbainjuries-1.1.0.dist-info/METADATA
nbainjuries-1.1.0.dist-info/WHEEL
nbainjuries-1.1.0.dist-info/licenses/LICENSE
nbainjuries-1.1.0.dist-info/RECORD
