Metadata-Version: 2.4
Name: nbainjuries
Version: 1.1.0
Summary: Library for accessing and extracting NBA player injury data from official team injury reports.
License: MIT
License-File: LICENSE
Keywords: nba,injuries,basketball,sports,analytics,sports science
Author: mxufc29
Author-email: mxufc29@outlook.com
Requires-Python: >=3.10,<4.0
Classifier: Intended Audience :: Science/Research
Classifier: Intended Audience :: Developers
Classifier: License :: OSI Approved :: MIT License
Classifier: Programming Language :: Python :: 3 :: Only
Classifier: Programming Language :: Python :: 3.10
Classifier: Operating System :: OS Independent
Classifier: Topic :: Software Development
Classifier: Topic :: Scientific/Engineering :: Information Analysis
Requires-Dist: PyPDF2 (>=3.0.1,<4.0)
Requires-Dist: aiohttp (>=3.9.3,<4.0)
Requires-Dist: jpype1 (>=1.5.2,<1.6.0)
Requires-Dist: pandas (>=2.2.3,<3.0)
Requires-Dist: requests (>=2.32.3,<3.0)
Requires-Dist: tabula-py (>=2.9.0,<3.0)
Project-URL: Documentation, https://github.com/mxufc29/nbainjuries/blob/main/Documentation.md
Project-URL: Homepage, https://github.com/mxufc29/nbainjuries
Project-URL: Source, https://github.com/mxufc29/nbainjuries
